lvmagp/__init__.py
lvmagp/__main__.py
lvmagp/actor/__init__.py
lvmagp/actor/actor.py
lvmagp/actor/commands/__init__.py
lvmagp/actor/commands/focus.py
lvmagp/actor/commands/guide.py
lvmagp/actor/commands/status.py
lvmagp/actor/statemachine.py
lvmagp/etc/lvm.sci.agp.yml
lvmagp/etc/lvm.skye.agp.yml
lvmagp/etc/lvm.skyw.agp.yml
lvmagp/etc/lvm.spec.agp.yml
lvmagp/exceptions.py
lvmagp/focus/__init__.py
lvmagp/focus/curvefit.py
lvmagp/focus/focus.py
lvmagp/focus/focusseries/__init__.py
lvmagp/focus/focusseries/base.py
lvmagp/focus/focusseries/photometry.py
lvmagp/focus/focusseries/projection.py
lvmagp/guide/calc/__init__.py
lvmagp/guide/calc/astrometry.py
lvmagp/guide/calc/base.py
lvmagp/guide/calc/simple.py
lvmagp/guide/offset/__init__.py
lvmagp/guide/offset/base.py
lvmagp/guide/offset/pwi.py
lvmagp/guide/worker.py
lvmagp/images/__init__.py
lvmagp/images/exceptions.py
lvmagp/images/image.py
lvmagp/images/processor.py
lvmagp/images/processors/__init__.py
lvmagp/images/processors/astrometry/__init__.py
lvmagp/images/processors/astrometry/astrometry.py
lvmagp/images/processors/astrometry/astrometrydotlocal.py
lvmagp/images/processors/background/__init__.py
lvmagp/images/processors/background/background.py
lvmagp/images/processors/background/daophot.py
lvmagp/images/processors/background/darkimage.py
lvmagp/images/processors/background/pysep.py
lvmagp/images/processors/detection/__init__.py
lvmagp/images/processors/detection/daophot.py
lvmagp/images/processors/detection/pysep.py
lvmagp/images/processors/detection/sourcedetection.py
lvmagp/json_serializers.py
sdss_lvmagp-0.3.6.dist-info/LICENSE.md
sdss_lvmagp-0.3.6.dist-info/METADATA
sdss_lvmagp-0.3.6.dist-info/WHEEL
sdss_lvmagp-0.3.6.dist-info/entry_points.txt
sdss_lvmagp-0.3.6.dist-info/RECORD
