Metadata-Version: 2.1
Name: sdss-lvmagp
Version: 0.3.6
Summary: Aquisition and guiding package for SDSS-V LVM
Home-page: https://github.com/sdss/lvmagp
License: BSD-3-Clause
Keywords: astronomy,software
Author: Hojae Ahn
Author-email: hojaeahn@khu.ac.kr
Requires-Python: >=3.8,<4
Classifier: Intended Audience :: Science/Research
Classifier: License :: OSI Approved :: BSD License
Classifier: Natural Language :: English
Classifier: Operating System :: OS Independent
Classifier: Programming Language :: Python :: 3
Classifier: Programming Language :: Python :: 3.8
Classifier: Programming Language :: Python :: 3.9
Classifier: Programming Language :: Python :: 3.10
Classifier: Programming Language :: Python :: 3.11
Classifier: Programming Language :: Python :: 3.10
Classifier: Programming Language :: Python :: 3.8
Classifier: Programming Language :: Python :: 3.9
Classifier: Topic :: Documentation :: Sphinx
Classifier: Topic :: Software Development :: Libraries :: Python Modules
Requires-Dist: aiohttp (>=3.7)
Requires-Dist: astrometry (>=4.1)
Requires-Dist: black (>=21.7-beta.0,<22.0)
Requires-Dist: lmfit (>=1.0)
Requires-Dist: pandas (>=1.1)
Requires-Dist: photutils (>=1.3.0)
Requires-Dist: scipy (>=1.7)
Requires-Dist: sdss-cluplus (>=0.0.16)
Requires-Dist: sdss-lvmtipo (>=0.0.10)
Requires-Dist: sep (>=1.2)
Project-URL: Documentation, https://sdss-lvmagp.readthedocs.org
Project-URL: Repository, https://github.com/sdss/lvmagp
